setup.cfg
setup.py
HSsound/_IEC61400.py
HSsound/_ISO3744hemiSphericalSurfaceWithOneReflectingPlane.py
HSsound/_ISO3744hemiSphericalSurfaceWithThreeReflectingPlane.py
HSsound/_ISO3744hemiSphericalSurfaceWithTwoReflectingPlane.py
HSsound/_ISO3744parallelPipedSurfaceWithOneReflectingPlaneUsingRectangularSegments.py
HSsound/_ISO3744parallelPipedSurfaceWithOneReflectingPlaneUsingTriangularSegments.py
HSsound/_ISO3744parallelPipedSurfaceWithThreeReflectingPlaneUsingRectangularSegments.py
HSsound/_ISO3744parallelPipedSurfaceWithThreeReflectingPlaneUsingTriangularSegments.py
HSsound/_ISO3744parallelPipedSurfaceWithTwoReflectingPlaneUsingRectangularSegments.py
HSsound/_ISO3744parallelPipedSurfaceWithTwoReflectingPlaneUsingTriangularSegments.py
HSsound/_ISO3746hemiSphericalSurfaceWithOneReflectingPlane.py
HSsound/_ISO3746hemiSphericalSurfaceWithThreeReflectingPlane.py
HSsound/_ISO3746hemiSphericalSurfaceWithTwoReflectingPlane.py
HSsound/_ISO3746parallelPipedSurfaceWithOneReflectingPlaneUsingRectangularSegments.py
HSsound/_ISO3746parallelPipedSurfaceWithOneReflectingPlaneUsingTriangularSegments.py
HSsound/_ISO3746parallelPipedSurfaceWithThreeReflectingPlaneUsingRectangularSegments.py
HSsound/_ISO3746parallelPipedSurfaceWithThreeReflectingPlaneUsingTriangularSegments.py
HSsound/_ISO3746parallelPipedSurfaceWithTwoReflectingPlaneUsingRectangularSegments.py
HSsound/_ISO3746parallelPipedSurfaceWithTwoReflectingPlaneUsingTriangularSegments.py
HSsound/__init__.py
HSsound.egg-info/PKG-INFO
HSsound.egg-info/SOURCES.txt
HSsound.egg-info/dependency_links.txt
HSsound.egg-info/requires.txt
HSsound.egg-info/top_level.txt